parqv/__init__.py
parqv/app.py
parqv/parqv.css
parqv/handlers/__init__.py
parqv/handlers/base_handler.py
parqv/handlers/json.py
parqv/handlers/parquet.py
parqv/views/__init__.py
parqv/views/data_view.py
parqv/views/metadata_view.py
parqv/views/schema_view.py
parqv-0.2.0.dist-info/licenses/LICENSE
parqv-0.2.0.dist-info/METADATA
parqv-0.2.0.dist-info/WHEEL
parqv-0.2.0.dist-info/entry_points.txt
parqv-0.2.0.dist-info/top_level.txt
parqv-0.2.0.dist-info/RECORD
