Metadata-Version: 2.4
Name: parqv
Version: 0.2.0
Summary: An interactive Python TUI for visualizing, exploring, and analyzing files directly in your terminal.
Author-email: Sangmin Yoon <sanspareilsmyn@gmail.com>
License-Expression: Apache-2.0
Requires-Python: >=3.10
License-File: LICENSE
Requires-Dist: textual>=1.0.0
Requires-Dist: pyarrow>=16.0.0
Requires-Dist: pandas>=2.0.0
Requires-Dist: numpy>=1.20.0
Requires-Dist: duckdb>=1.2.0
Dynamic: license-file
